{
  "DateRange" :  ["DateTime", "DateTime"],
  "Tags": [
    {
      "ID": 1,
      "Name": "string"
    }
  ],
  "incomeRecords": [
    {
      "ID": 1,
      "Category": "string",
      "Date": "DateTime",
      "Amount": 1.0,
      "Frequency": "string",
      "Source": "string"
    }
  ],
  "expenseRecords": [
    {
      "ID": 1,
      "Category": "string",
      "Date": "DateTime",
      "Amount": 1.0,
      "Frequency": "string",
      "Notes": "string",
      "TagIDs": [
        1,
        2,
        3
      ]
    }
  ]
}